Orange3_HXLvisualETL-0.3.0rc1-py3.8-nspkg.pth
Orange3_HXLvisualETL-0.3.0rc1.data/data/help/orange3-example/.buildinfo
Orange3_HXLvisualETL-0.3.0rc1.data/data/help/orange3-example/genindex.html
Orange3_HXLvisualETL-0.3.0rc1.data/data/help/orange3-example/index.html
Orange3_HXLvisualETL-0.3.0rc1.data/data/help/orange3-example/objects.inv
Orange3_HXLvisualETL-0.3.0rc1.data/data/help/orange3-example/search.html
Orange3_HXLvisualETL-0.3.0rc1.data/data/help/orange3-example/searchindex.js
Orange3_HXLvisualETL-0.3.0rc1.data/data/help/orange3-example/_sources/index.rst.txt
Orange3_HXLvisualETL-0.3.0rc1.data/data/help/orange3-example/_sources/widgets/mywidget.md.txt
Orange3_HXLvisualETL-0.3.0rc1.data/data/help/orange3-example/_static/_sphinx_javascript_frameworks_compat.js
Orange3_HXLvisualETL-0.3.0rc1.data/data/help/orange3-example/_static/basic.css
Orange3_HXLvisualETL-0.3.0rc1.data/data/help/orange3-example/_static/doctools.js
Orange3_HXLvisualETL-0.3.0rc1.data/data/help/orange3-example/_static/documentation_options.js
Orange3_HXLvisualETL-0.3.0rc1.data/data/help/orange3-example/_static/file.png
Orange3_HXLvisualETL-0.3.0rc1.data/data/help/orange3-example/_static/jquery-3.6.0.js
Orange3_HXLvisualETL-0.3.0rc1.data/data/help/orange3-example/_static/jquery.js
Orange3_HXLvisualETL-0.3.0rc1.data/data/help/orange3-example/_static/language_data.js
Orange3_HXLvisualETL-0.3.0rc1.data/data/help/orange3-example/_static/minus.png
Orange3_HXLvisualETL-0.3.0rc1.data/data/help/orange3-example/_static/nature.css
Orange3_HXLvisualETL-0.3.0rc1.data/data/help/orange3-example/_static/plus.png
Orange3_HXLvisualETL-0.3.0rc1.data/data/help/orange3-example/_static/pygments.css
Orange3_HXLvisualETL-0.3.0rc1.data/data/help/orange3-example/_static/searchtools.js
Orange3_HXLvisualETL-0.3.0rc1.data/data/help/orange3-example/_static/underscore-1.13.1.js
Orange3_HXLvisualETL-0.3.0rc1.data/data/help/orange3-example/_static/underscore.js
Orange3_HXLvisualETL-0.3.0rc1.dist-info/METADATA
Orange3_HXLvisualETL-0.3.0rc1.dist-info/WHEEL
Orange3_HXLvisualETL-0.3.0rc1.dist-info/entry_points.txt
Orange3_HXLvisualETL-0.3.0rc1.dist-info/namespace_packages.txt
Orange3_HXLvisualETL-0.3.0rc1.dist-info/top_level.txt
Orange3_HXLvisualETL-0.3.0rc1.dist-info/RECORD
