Metadata-Version: 2.1
Name: Orange3-HXLvisualETL
Version: 0.3.0rc1
Summary: Humanitarian Exchange Language (HXL) visual Extract, Transform, Load (ETL)
Home-page: https://github.com/fititnt/orange3-hxl
Author: EticaAI
Author-email: rocha@ieee.org
License: Unlicence
Keywords: orange3 add-on,hxl
Requires-Dist: Orange3
